fexcel/__init__.py
fexcel/__main__.py
fexcel/generator.py
fexcel/py.typed
fexcel/fields/__init__.py
fexcel/fields/base.py
fexcel/fields/boolean.py
fexcel/fields/choice.py
fexcel/fields/network.py
fexcel/fields/numeric.py
fexcel/fields/temporal.py
fexcel/fields/text.py
fexcel-0.0.6.dist-info/METADATA
fexcel-0.0.6.dist-info/WHEEL
fexcel-0.0.6.dist-info/entry_points.txt
fexcel-0.0.6.dist-info/licenses/LICENSE
fexcel-0.0.6.dist-info/RECORD
