Metadata-Version: 2.4
Name: fexcel
Version: 0.0.6
Summary: A simple Excel files mocker based on faker and pyexcel
Author-email: Manel Caireta <m.caireta@altostratus.es>
License-File: LICENSE
Requires-Python: >=3.10
Requires-Dist: faker>=36.2.2
Requires-Dist: pyexcel>=0.7.1
Provides-Extra: all
Requires-Dist: chardet>=5.2.0; extra == 'all'
Requires-Dist: pyexcel-io>=0.6.7; extra == 'all'
Requires-Dist: pyexcel-ods3>=0.6.1; extra == 'all'
Requires-Dist: pyexcel-xls>=0.7.1; extra == 'all'
Requires-Dist: pyexcel-xlsx>=0.6.1; extra == 'all'
Provides-Extra: csv
Requires-Dist: chardet>=5.2.0; extra == 'csv'
Requires-Dist: pyexcel-io>=0.6.7; extra == 'csv'
Provides-Extra: ods
Requires-Dist: pyexcel-ods3>=0.6.1; extra == 'ods'
Provides-Extra: xls
Requires-Dist: pyexcel-xls>=0.7.1; extra == 'xls'
Provides-Extra: xlsx
Requires-Dist: pyexcel-xlsx>=0.6.1; extra == 'xlsx'
